{"status":"done","publicPath":"http://127.0.0.1:8080/","chunks":{"app":[{"name":"bundle.js","publicPath":"http://127.0.0.1:8080/bundle.js","path":"C:\\Users\\russe\\Documents\\Russell\\cogito\\cogito\\frontend\\dist\\bundle.js"},{"name":"app.de70123871c68badfe65.hot-update.js","publicPath":"http://127.0.0.1:8080/app.de70123871c68badfe65.hot-update.js","path":"C:\\Users\\russe\\Documents\\Russell\\cogito\\cogito\\frontend\\dist\\app.de70123871c68badfe65.hot-update.js"}]},"error":"ModuleError","message":"Module Error (from ./node_modules/eslint-loader/index.js):\n\nC:\\Users\\russe\\Documents\\Russell\\cogito\\cogito\\frontend\\src\\common\\api.service.js\n   1:43  warning  Delete `␍`                                                                                         prettier/prettier\n   2:1   warning  Delete `␍`                                                                                         prettier/prettier\n   3:35  warning  Delete `␍`                                                                                         prettier/prettier\n   4:42  warning  Delete `␍`                                                                                         prettier/prettier\n   5:26  warning  Delete `␍`                                                                                         prettier/prettier\n   6:2   warning  Delete `␍`                                                                                         prettier/prettier\n   7:1   warning  Delete `␍`                                                                                         prettier/prettier\n   8:46  warning  Delete `␍`                                                                                         prettier/prettier\n   9:19  warning  Delete `␍`                                                                                         prettier/prettier\n  10:29  warning  Delete `␍`                                                                                         prettier/prettier\n  11:60  warning  Delete `␍`                                                                                         prettier/prettier\n  12:15  warning  Delete `␍`                                                                                         prettier/prettier\n  13:42  warning  Delete `␍`                                                                                         prettier/prettier\n  14:39  error    'POST' is not defined                                                                              no-undef\n  14:44  warning  Replace `·GET,·OPTIONS,·PUT,·DELETE,␍` with `⏎······GET,⏎······OPTIONS,⏎······PUT,⏎······DELETE,`  prettier/prettier\n  14:45  error    'GET' is not defined                                                                               no-undef\n  14:50  error    'OPTIONS' is not defined                                                                           no-undef\n  14:59  error    'PUT' is not defined                                                                               no-undef\n  14:64  error    'DELETE' is not defined                                                                            no-undef\n  15:54  warning  Delete `␍`                                                                                         prettier/prettier\n  16:43  warning  Delete `␍`                                                                                         prettier/prettier\n  17:33  warning  Delete `␍`                                                                                         prettier/prettier\n  18:7   warning  Delete `␍`                                                                                         prettier/prettier\n  19:5   warning  Delete `␍`                                                                                         prettier/prettier\n  20:33  warning  Delete `␍`                                                                                         prettier/prettier\n  21:19  warning  Delete `␍`                                                                                         prettier/prettier\n  22:43  warning  Delete `␍`                                                                                         prettier/prettier\n  23:2   warning  Delete `␍`                                                                                         prettier/prettier\n  24:1   warning  Delete `␍`                                                                                         prettier/prettier\n  25:23  warning  Delete `␍`                                                                                         prettier/prettier\n\n✖ 30 problems (5 errors, 25 warnings)\n  0 errors and 25 warnings potentially fixable with the `--fix` option.\n"}